smartthings_basic_rest/__init__.py
smartthings_basic_rest-0.1.4.dist-info/METADATA
smartthings_basic_rest-0.1.4.dist-info/WHEEL
smartthings_basic_rest-0.1.4.dist-info/top_level.txt
smartthings_basic_rest-0.1.4.dist-info/RECORD
