Metadata-Version: 2.1
Name: smartthings_basic_rest
Version: 0.1.4
Summary: SmartThings Plug API
License: MIT
